_runtime.abi3.so
koi_cuda111-0.0.5.dist-info/WHEEL
koi_cuda111-0.0.5.dist-info/METADATA
koi_cuda111-0.0.5.dist-info/RECORD
koi_cuda111-0.0.5.dist-info/top_level.txt
koi/decode.py
koi/utils.py
koi/build.py
koi/lstm.py
koi/__init__.py
koi/test/__init__.py
koi/test/test_lstm.py
koi_cuda111.libs/lib-b204c20e.so
